adb_tools/app_helper.py
adb_tools/device_helper.py
adb_tools/log_compiler.py
adb_tools/logcat_traces.py
adb_tools/page_helper.py
adb_tools/providers/anr.py
adb_tools/providers/crash.py
adb_tools/providers/custom_exception.py
adb_tools/providers/environment.py
adb_tools-1.1.2.dist-info/METADATA
adb_tools-1.1.2.dist-info/WHEEL
adb_tools-1.1.2.dist-info/top_level.txt
adb_tools-1.1.2.dist-info/RECORD
