Metadata-Version: 2.1
Name: adb-tools
Version: 1.1.2
Summary: adb tools
Home-page: UNKNOWN
Author: crystal
Author-email: zhuhuiping@shizhuang-inc.com
License: Apache License 2.0
Platform: UNKNOWN
Requires-Python: >=3.7
